{
	"info": {
		"_postman_id": "7ac97c40-fa2f-44a9-9b51-1c3f00fd7b1c",
		"name": "Stepik Course Mock",
		"schema": "https://schema.getpostman.com/json/collection/v2.1.0/collection.json",
		"_exporter_id": "25897606"
	},
	"item": [
		{
			"name": "users",
			"protocolProfileBehavior": {
				"disableBodyPruning": true
			},
			"request": {
				"method": "GET",
				"header": [],
				"body": {
					"mode": "raw",
					"raw": ""
				},
				"url": {
					"raw": "{{url}}/users",
					"host": [
						"{{url}}"
					],
					"path": [
						"users"
					]
				}
			},
			"response": [
				{
					"name": "Default",
					"originalRequest": {
						"method": "GET",
						"header": [],
						"body": {
							"mode": "raw",
							"raw": ""
						},
						"url": {
							"raw": "{{url}}/users?limit=3&gender=woman",
							"host": [
								"{{url}}"
							],
							"path": [
								"users"
							],
							"query": [
								{
									"key": "limit",
									"value": "3"
								},
								{
									"key": "gender",
									"value": "woman"
								}
							]
						}
					},
					"code": 200,
					"_postman_previewlanguage": null,
					"header": null,
					"cookie": [],
					"body": "{\r\n    \"users\": [\r\n        {\r\n            \"userId\":   1,\r\n            \"userName\": \"Anna\",\r\n            \"userAge\":  28\r\n        },\r\n        {\r\n            \"userId\":   2,\r\n            \"userName\": \"Andrey\",\r\n            \"userAge\":  34\r\n        },\r\n        {\r\n            \"userId\":   3,\r\n            \"userName\": \"Elena\",\r\n            \"userAge\":  null\r\n        }\r\n    ]\r\n}"
				},
				{
					"name": "limit=2, gender=woman",
					"originalRequest": {
						"method": "GET",
						"header": [],
						"body": {
							"mode": "raw",
							"raw": ""
						},
						"url": {
							"raw": "{{url}}/users?limit=2&gender=woman",
							"host": [
								"{{url}}"
							],
							"path": [
								"users"
							],
							"query": [
								{
									"key": "limit",
									"value": "2"
								},
								{
									"key": "gender",
									"value": "woman"
								}
							]
						}
					},
					"code": 200,
					"_postman_previewlanguage": null,
					"header": null,
					"cookie": [],
					"body": "{\r\n    \"users\": [\r\n        {\r\n            \"userId\":   1,\r\n            \"userName\": \"Anna\",\r\n            \"userAge\":  28\r\n        },\r\n        {\r\n            \"userId\":   3,\r\n            \"userName\": \"Elena\",\r\n            \"userAge\":  null\r\n        },\r\n    ]\r\n}"
				},
				{
					"name": "limit=1, gender=woman",
					"originalRequest": {
						"method": "GET",
						"header": [],
						"body": {
							"mode": "raw",
							"raw": ""
						},
						"url": {
							"raw": "{{url}}/users?limit=1&gender=woman",
							"host": [
								"{{url}}"
							],
							"path": [
								"users"
							],
							"query": [
								{
									"key": "limit",
									"value": "1"
								},
								{
									"key": "gender",
									"value": "woman"
								}
							]
						}
					},
					"code": 200,
					"_postman_previewlanguage": null,
					"header": null,
					"cookie": [],
					"body": "{\r\n    \"users\": [\r\n        {\r\n            \"userId\":   1,\r\n            \"userName\": \"Anna\",\r\n            \"userAge\":  28\r\n        },\r\n        {\r\n            \"userId\":   3,\r\n            \"userName\": \"Elena\",\r\n            \"userAge\":  null\r\n        },\r\n    ]\r\n}"
				},
				{
					"name": "Without query",
					"originalRequest": {
						"method": "GET",
						"header": [],
						"body": {
							"mode": "raw",
							"raw": ""
						},
						"url": {
							"raw": "{{url}}/users",
							"host": [
								"{{url}}"
							],
							"path": [
								"users"
							],
							"query": [
								{
									"key": "limit",
									"value": "3",
									"disabled": true
								},
								{
									"key": "gender",
									"value": "woman",
									"disabled": true
								}
							]
						}
					},
					"code": 200,
					"_postman_previewlanguage": null,
					"header": null,
					"cookie": [],
					"body": "{\r\n    \"users\": [\r\n        {\r\n            \"userId\":   1,\r\n            \"userName\": \"Anna\",\r\n            \"userAge\":  28\r\n        },\r\n        {\r\n            \"userId\":   3,\r\n            \"userName\": \"Elena\",\r\n            \"userAge\":  null\r\n        },\r\n    ]\r\n}"
				}
			]
		},
		{
			"name": "users",
			"request": {
				"method": "POST",
				"header": [],
				"body": {
					"mode": "raw",
					"raw": ""
				},
				"url": {
					"raw": "{{url}}/users",
					"host": [
						"{{url}}"
					],
					"path": [
						"users"
					]
				}
			},
			"response": [
				{
					"name": "Default",
					"originalRequest": {
						"method": "POST",
						"header": [],
						"body": {
							"mode": "raw",
							"raw": ""
						},
						"url": {
							"raw": "{{url}}/users",
							"host": [
								"{{url}}"
							],
							"path": [
								"users"
							]
						}
					},
					"code": 201,
					"_postman_previewlanguage": null,
					"header": null,
					"cookie": [],
					"body": ""
				}
			]
		},
		{
			"name": "users",
			"request": {
				"method": "PUT",
				"header": [],
				"body": {
					"mode": "raw",
					"raw": ""
				},
				"url": {
					"raw": "{{url}}/users",
					"host": [
						"{{url}}"
					],
					"path": [
						"users"
					]
				}
			},
			"response": [
				{
					"name": "Default",
					"originalRequest": {
						"method": "PUT",
						"header": [],
						"body": {
							"mode": "raw",
							"raw": ""
						},
						"url": {
							"raw": "{{url}}/users",
							"host": [
								"{{url}}"
							],
							"path": [
								"users"
							]
						}
					},
					"code": 200,
					"_postman_previewlanguage": null,
					"header": null,
					"cookie": [],
					"body": ""
				}
			]
		},
		{
			"name": "cars",
			"protocolProfileBehavior": {
				"disableBodyPruning": true
			},
			"request": {
				"method": "GET",
				"header": [],
				"body": {
					"mode": "raw",
					"raw": ""
				},
				"url": {
					"raw": "{{url}}/cars",
					"host": [
						"{{url}}"
					],
					"path": [
						"cars"
					]
				}
			},
			"response": [
				{
					"name": "Default",
					"originalRequest": {
						"method": "GET",
						"header": [],
						"body": {
							"mode": "raw",
							"raw": ""
						},
						"url": {
							"raw": "{{url}}/cars",
							"host": [
								"{{url}}"
							],
							"path": [
								"cars"
							]
						}
					},
					"code": 200,
					"_postman_previewlanguage": null,
					"header": null,
					"cookie": [],
					"body": ""
				}
			]
		},
		{
			"name": "pets",
			"protocolProfileBehavior": {
				"disableBodyPruning": true
			},
			"request": {
				"method": "GET",
				"header": [],
				"body": {
					"mode": "raw",
					"raw": ""
				},
				"url": {
					"raw": "{{url}}/pets",
					"host": [
						"{{url}}"
					],
					"path": [
						"pets"
					]
				}
			},
			"response": [
				{
					"name": "Default",
					"originalRequest": {
						"method": "GET",
						"header": [],
						"body": {
							"mode": "raw",
							"raw": ""
						},
						"url": {
							"raw": "{{url}}/pets",
							"host": [
								"{{url}}"
							],
							"path": [
								"pets"
							]
						}
					},
					"code": 200,
					"_postman_previewlanguage": null,
					"header": null,
					"cookie": [],
					"body": ""
				}
			]
		},
		{
			"name": "pets",
			"request": {
				"method": "DELETE",
				"header": [],
				"body": {
					"mode": "raw",
					"raw": ""
				},
				"url": {
					"raw": "{{url}}/pets",
					"host": [
						"{{url}}"
					],
					"path": [
						"pets"
					]
				}
			},
			"response": [
				{
					"name": "Default",
					"originalRequest": {
						"method": "DELETE",
						"header": [],
						"body": {
							"mode": "raw",
							"raw": ""
						},
						"url": {
							"raw": "{{url}}/pets",
							"host": [
								"{{url}}"
							],
							"path": [
								"pets"
							]
						}
					},
					"code": 204,
					"_postman_previewlanguage": null,
					"header": null,
					"cookie": [],
					"body": ""
				}
			]
		}
	],
	"variable": [
		{
			"key": "url",
			"value": "https://85db0130-4e0b-4248-95b2-82d554af131f.mock.pstmn.io"
		}
	]
}